rdat_kit/__init__.py
rdat_kit/handler.py
rdat_kit/util.py
rdat_kit-1.6.3.dist-info/LICENSE
rdat_kit-1.6.3.dist-info/METADATA
rdat_kit-1.6.3.dist-info/WHEEL
rdat_kit-1.6.3.dist-info/top_level.txt
rdat_kit-1.6.3.dist-info/RECORD
