Metadata-Version: 2.1
Name: rdat-kit
Version: 1.6.3
Summary: RDATKit is a utility library for reading and writing RDAT files that describe RNA structure mapping experiments
Author-email: Das Lab <thedaslab@stanford.edu>
Project-URL: Homepage, https://github.com/ribokit/rdatkit
Project-URL: Documentation, https://ribokit.github.io/RDATKit/
Project-URL: Bug Tracker, https://github.com/ribokit/rdatkit/issues
Classifier: Programming Language :: Python :: 3
Classifier: License :: OSI Approved :: MIT License
Classifier: Operating System :: OS Independent
Requires-Python: >=3.7
License-File: LICENSE
Requires-Dist: xlwt
Requires-Dist: xlrd
